mailbot/exceptions.py
mailbot/callback.py
mailbot/mailbot.py
mailbot/__init__.py
mailbot/compat.py
mailbot/livetests/test_mail_received.py
mailbot/livetests/__init__.py
mailbot/tests/test_init.py
mailbot/tests/test_callback.py
mailbot/tests/test_mailbot.py
mailbot/tests/__init__.py
mailbot/tests/mails/mail_with_attachment.txt
mailbot/tests/mails/mail_encoded_headers.txt
mailbot-0.3.dist-info/METADATA
mailbot-0.3.dist-info/WHEEL
mailbot-0.3.dist-info/top_level.txt
mailbot-0.3.dist-info/DESCRIPTION.rst
mailbot-0.3.dist-info/pydist.json
mailbot-0.3.dist-info/RECORD
