Metadata-Version: 2.0
Name: mailbot
Version: 0.3
Summary: MailBot: execute callback on mail reception
Home-page: https://github.com/magopian/mailbot
Author: Mathieu Agopian
Author-email: mathieu.agopian@gmail.com
License: BSD Licence
Keywords: m,a,i,l, ,c,a,l,l,b,a,c,k
Platform: UNKNOWN
Classifier: Development Status :: 3 - Alpha
Classifier: Environment :: Console
Classifier: Intended Audience :: Developers
Classifier: License :: OSI Approved :: BSD License
Classifier: Natural Language :: English
Classifier: Programming Language :: Python
Classifier: Programming Language :: Python :: 2
Classifier: Programming Language :: Python :: 2.7
Classifier: Programming Language :: Python :: 3
Classifier: Programming Language :: Python :: 3.3
Requires-Dist: imapclient
